streamlit_excel/__init__.py
streamlit_excel/version.py
streamlit_excel-0.0.2.dist-info/LICENSE
streamlit_excel-0.0.2.dist-info/METADATA
streamlit_excel-0.0.2.dist-info/WHEEL
streamlit_excel-0.0.2.dist-info/top_level.txt
streamlit_excel-0.0.2.dist-info/RECORD
