Metadata-Version: 2.1
Name: streamlit-excel
Version: 0.0.2
Summary: Build Excel-style filter widgets for large pandas DataFrames in Streamlit
Home-page: https://github.com/sbslee/streamlit-excel
Author: Seung-been "Steven" Lee
Author-email: sbstevenlee@gmail.com
License: MIT
License-File: LICENSE
